saveable_objects/__init__.py
saveable_objects/_meta_class.py
saveable_objects/_saveable_object.py
saveable_objects/_saveable_object_3_7.py
saveable_objects/checkpointing/__init__.py
saveable_objects/checkpointing/_checkpointing.py
saveable_objects/checkpointing/_checkpointing.pyi
saveable_objects/checkpointing/_checkpointing_3_7.py
saveable_objects/extensions/__init__.py
saveable_objects/extensions/_extensions.py
saveable_objects/extensions/_extensions.pyi
saveable_objects-1.1.8.dist-info/METADATA
saveable_objects-1.1.8.dist-info/WHEEL
saveable_objects-1.1.8.dist-info/licenses/LICENSE
saveable_objects-1.1.8.dist-info/RECORD
